pyradigms/__init__.py
pyradigms-0.1.0.dist-info/LICENSE
pyradigms-0.1.0.dist-info/METADATA
pyradigms-0.1.0.dist-info/WHEEL
pyradigms-0.1.0.dist-info/top_level.txt
pyradigms-0.1.0.dist-info/RECORD
